chemkin/__init__.py
chemkin/chemkin.py
chemkin207/__init__.py
chemkin207/_tester.py
chemkin207/chemkin207.py
chemkin207/supporting/COEF.sqlite
chemkin207/tests/__init__.py
chemkin207/tests/test_chemkin207.py
chemkin207/tests/test_tables/multireaction.tex
chemkin207/tests/test_tables/multireaction_check.tex
chemkin207/tests/test_xmls/reaction_arr_over_1.xml
chemkin207/tests/test_xmls/reaction_arr_over_2.xml
chemkin207/tests/test_xmls/reaction_coef_1.xml
chemkin207/tests/test_xmls/reaction_init_type_1.xml
chemkin207/tests/test_xmls/reaction_init_value_1.xml
chemkin207/tests/test_xmls/reaction_init_value_2.xml
chemkin207/tests/test_xmls/reaction_rate_1.xml
chemkin207/tests/test_xmls/rxns.xml
chemkin207/tests/test_xmls/rxns_rev.xml
chemkin207/tests/test_xmls/rxns_rev_ob_test.xml
chemkin207/tests/test_xmls/rxns_test_empty_file.xml
chemkin207/tests/test_xmls/rxns_test_missing_arrhenius_parameters.xml
chemkin207/tests/test_xmls/rxns_test_missing_constant_parameters.xml
chemkin207/tests/test_xmls/rxns_test_missing_modified_arrhenius_parameters.xml
chemkin207/tests/test_xmls/rxns_test_missing_reactants.xml
chemkin207/tests/test_xmls/rxns_test_missing_reactions.xml
chemkin207/tests/test_xmls/rxns_test_missing_species.xml
chemkin207/tests/test_xmls/rxns_test_reversible_input.xml
chemkin207/tests/test_xmls/rxns_test_reversible_missing_tag.xml
chemkin207/tests/test_xmls/rxns_test_reversible_tag_error.xml
chemkin207/tests/test_xmls/rxns_test_type_missing_tag.xml
chemkin207/tests/test_xmls/rxns_test_unexpected_reactant.xml
chemkin207-0.1.13.dist-info/DESCRIPTION.rst
chemkin207-0.1.13.dist-info/METADATA
chemkin207-0.1.13.dist-info/RECORD
chemkin207-0.1.13.dist-info/WHEEL
chemkin207-0.1.13.dist-info/metadata.json
chemkin207-0.1.13.dist-info/top_level.txt
