Metadata-Version: 2.0
Name: chemkin207
Version: 0.1.13
Summary: Simple chemical kinetics library.
Home-page: https://github.com/cs207-g1/cs207-FinalProject
Author: Paul Blankley, Ryan Janssen, Boyuan Sun
Author-email: pblankley@g.harvard.edu
License: MIT
Download-URL: https://github.com/cs207-g1/cs207-FinalProject/tarball/0.1.13
Keywords: chemical kinetics
Platform: UNKNOWN
Classifier: Programming Language :: Python :: 3
Classifier: Programming Language :: Python :: 3.3
Classifier: Programming Language :: Python :: 3.4
Classifier: Programming Language :: Python :: 3.5
Classifier: Programming Language :: Python :: 3.6
Classifier: Intended Audience :: Science/Research
Classifier: License :: OSI Approved :: MIT License
